cctx/__init__.py
cctx/file_content.py
cctx/file_tree.py
cctx/main.py
cat_context-1.0.0.dist-info/LICENSE
cat_context-1.0.0.dist-info/METADATA
cat_context-1.0.0.dist-info/WHEEL
cat_context-1.0.0.dist-info/entry_points.txt
cat_context-1.0.0.dist-info/top_level.txt
cat_context-1.0.0.dist-info/RECORD
