Metadata-Version: 2.1
Name: cat-context
Version: 1.0.0
Summary: A command-line tool to print file trees and display file contents.
Home-page: https://github.com/asnunes/cat-context
Author: Alexandre Nunes
Author-email: alexandrenunes@poli.ufrj.br
License: MIT
Classifier: Programming Language :: Python :: 3
Classifier: License :: OSI Approved :: MIT License
Classifier: Operating System :: OS Independent
Requires-Python: >=3.7
License-File: LICENSE
